ProText/Textprocess.py
ProText/__init__.py
ProText-0.0.4.dist-info/LICENSE.txt
ProText-0.0.4.dist-info/METADATA
ProText-0.0.4.dist-info/WHEEL
ProText-0.0.4.dist-info/top_level.txt
ProText-0.0.4.dist-info/RECORD
