Metadata-Version: 2.1
Name: ProText
Version: 0.0.4
Summary: A text Preprocessing & Feature extraction package for NLP applications
Home-page: https://github.com/Rajanna-AI/Unstructured-Data/tree/main/Assignments/ProText
Author: Rajanna
Author-email: krajanna@gmail.com
License: UNKNOWN
Platform: UNKNOWN
Classifier: Programming Language :: Python :: 3
Classifier: License :: OSI Approved :: MIT License
Classifier: Operating System :: OS Independent
Requires-Python: >=3.6
Requires-Dist: nltk
Requires-Dist: textblob
Requires-Dist: wordcloud
Requires-Dist: matplotlib
Requires-Dist: scikit-learn
